data_memory/data_memory.sv
module data_memory #(
parameter W = 32,
parameter N=5
)(
    input logic clk,

    input logic [N-1:0] address, //direcición de 'consulta 1'
    input logic rst,
    input logic MemRead, //habilitación de lectura
    input logic MemWrite, //habilitación de escritura
    input logic [W-1:0] write_data, //valor de almacenamiento
    
    //a la salida mostramos el contenido de la memoria
    output logic [W-1:0] read_data
);
//creamos propiamente el registro: 
reg  [W-1:0] mem[(2**N)-1:0] ;


always_ff @(posedge clk) begin
    if (rst) begin
        foreach (mem[i])begin
            mem[i] <= 0;
        end
        read_data <= 0;
    end
    else begin
    if (MemWrite) mem[address]<=write_data;
    if (MemRead) read_data <= mem[address];
    end
end

endmodule

data_memory/data_memory_tb.sv
`timescale 100ns / 1ps
module data_memory_tb;

    // Parámetros del módulo
    parameter W = 32;
    parameter N = 5;
    
    // Definición de señales
    logic clk;
    logic [N-1:0] address;
    logic [W-1:0] write_data;
    logic [W-1:0] read_data; 
    logic MemRead;
    logic MemWrite;
    logic rst;

    // Instancia del módulo bajo prueba
    data_memory #(W, N) dut (
        .rst(rst),
        .clk(clk),
        .address(address),
        .MemWrite(MemWrite),
        .MemRead(MemRead),
        .write_data(write_data),
        .read_data(read_data)
    );

    // Generación de clock a 1 kHz
    always #1 clk = ~clk;

    initial begin
        $dumpfile("data_memory.vcd");
        $dumpvars(0, data_memory_tb);
    end

    // Test case: Escribir en todas dlas posibles direcciones y verificar
    initial begin
        rst = 1;
        clk = 0;
        @(posedge clk); // Esperar un poco para estabilizar la simulación
        rst <= 0;

        // Escribir datos en todas las posibles direcciones de memoria
        for (integer i = 0; i < (1 << N); i++) begin
            address = i; // Dirección de memoria
            @(posedge clk);
            write_data = $random; // Datos aleatorios a escribir
            MemWrite = 1; // Habilitación de escritura
            @(posedge clk);
        end
        MemWrite = 0;
        
        // Leer datos de todas las direcciones de memoria y verificar si son correctos
        for (integer i = 0; i < (1 << N); i++) begin
            address = i; // Dirección de memoria
            @(posedge clk);
            MemRead = 1;
            @(posedge clk);
            if (read_data !== dut.mem[i]) begin
                $display("Test case failed at address %d", i);
            end else begin
                $display("Mem %0d: %h", i, read_data);
                end
        end
        @(posedge clk); // Esperar un poco al final antes de finalizar la simulación
        $finish; // Finalizar la simulación
    end

endmodule

data_memory/data_memory.vcd
$date
	Thu Apr 04 14:29:44 2024
$end
$version
	Icarus Verilog
$end
$timescale
	1ps
$end
$scope module data_memory_tb $end
$var wire 32 ! read_data [31:0] $end
$var parameter 32 " N $end
$var parameter 32 # W $end
$var reg 1 $ MemRead $end
$var reg 1 % MemWrite $end
$var reg 5 & address [4:0] $end
$var reg 1 ' clk $end
$var reg 1 ( rst $end
$var reg 32 ) write_data [31:0] $end
$scope module dut $end
$var wire 1 $ MemRead $end
$var wire 1 % MemWrite $end
$var wire 5 * address [4:0] $end
$var wire 1 ' clk $end
$var wire 1 ( rst $end
$var wire 32 + write_data [31:0] $end
$var parameter 32 , N $end
$var parameter 32 - W $end
$var reg 32 . read_data [31:0] $end
$scope begin $ivl_foreach0 $end
$var integer 32 / i [31:0] $end
$upscope $end
$upscope $end
$scope begin $ivl_for_loop0 $end
$var integer 32 0 i [31:0] $end
$upscope $end
$scope begin $ivl_for_loop1 $end
$var integer 32 1 i [31:0] $end
$upscope $end
$upscope $end
$enddefinitions $end
$comment Show the parameter values. $end
$dumpall
b100000 -
b101 ,
b100000 #
b101 "
$end
#0
$dumpvars
bx 1
bx 0
b0 /
bx .
bx +
bx *
bx )
1(
0'
bx &
x%
x$
bx !
$end
#100000
b0 !
b0 .
0(
b0 &
b0 *
b0 0
b100000 /
1'
#200000
0'
#300000
1%
b10010000101010011010100100100 )
b10010000101010011010100100100 +
1'
#400000
0'
#500000
b1 &
b1 *
b1 0
1'
#600000
0'
#700000
b11000000100010010101111010000001 )
b11000000100010010101111010000001 +
1'
#800000
0'
#900000
b10 &
b10 *
b10 0
1'
#1000000
0'
#1100000
b10000100100001001101011000001001 )
b10000100100001001101011000001001 +
1'
#1200000
0'
#1300000
b11 &
b11 *
b11 0
1'
#1400000
0'
#1500000
b10110001111100000101011001100011 )
b10110001111100000101011001100011 +
1'
#1600000
0'
#1700000
b100 &
b100 *
b100 0
1'
#1800000
0'
#1900000
b110101110010111101100001101 )
b110101110010111101100001101 +
1'
#2000000
0'
#2100000
b101 &
b101 *
b101 0
1'
#2200000
0'
#2300000
b1000110110111111001100110001101 )
b1000110110111111001100110001101 +
1'
#2400000
0'
#2500000
b110 &
b110 *
b110 0
1'
#2600000
0'
#2700000
b10110010110000101000010001100101 )
b10110010110000101000010001100101 +
1'
#2800000
0'
#2900000
b111 &
b111 *
b111 0
1'
#3000000
0'
#3100000
b10001001001101110101001000010010 )
b10001001001101110101001000010010 +
1'
#3200000
0'
#3300000
b1000 &
b1000 *
b1000 0
1'
#3400000
0'
#3500000
b111100111110001100000001 )
b111100111110001100000001 +
1'
#3600000
0'
#3700000
b1001 &
b1001 *
b1001 0
1'
#3800000
0'
#3900000
b110110101111100110100001101 )
b110110101111100110100001101 +
1'
#4000000
0'
#4100000
b1010 &
b1010 *
b1010 0
1'
#4200000
0'
#4300000
b111011001000111111000101110110 )
b111011001000111111000101110110 +
1'
#4400000
0'
#4500000
b1011 &
b1011 *
b1011 0
1'
#4600000
0'
#4700000
b11110100011011100110100111101 )
b11110100011011100110100111101 +
1'
#4800000
0'
#4900000
b1100 &
b1100 *
b1100 0
1'
#5000000
0'
#5100000
b1110110110101000101011111101101 )
b1110110110101000101011111101101 +
1'
#5200000
0'
#5300000
b1101 &
b1101 *
b1101 0
1'
#5400000
0'
#5500000
b1000110001011011111011110001100 )
b1000110001011011111011110001100 +
1'
#5600000
0'
#5700000
b1110 &
b1110 *
b1110 0
1'
#5800000
0'
#5900000
b1111100111111011110100111111001 )
b1111100111111011110100111111001 +
1'
#6000000
0'
#6100000
b1111 &
b1111 *
b1111 0
1'
#6200000
0'
#6300000
b11100011001101110010010011000110 )
b11100011001101110010010011000110 +
1'
#6400000
0'
#6500000
b10000 &
b10000 *
b10000 0
1'
#6600000
0'
#6700000
b11100010111101111000010011000101 )
b11100010111101111000010011000101 +
1'
#6800000
0'
#6900000
b10001 &
b10001 *
b10001 0
1'
#7000000
0'
#7100000
b11010101000100111101001010101010 )
b11010101000100111101001010101010 +
1'
#7200000
0'
#7300000
b10010 &
b10010 *
b10010 0
1'
#7400000
0'
#7500000
b1110010101011111111011111100101 )
b1110010101011111111011111100101 +
1'
#7600000
0'
#7700000
b10011 &
b10011 *
b10011 0
1'
#7800000
0'
#7900000
b10111011110100100111001001110111 )
b10111011110100100111001001110111 +
1'
#8000000
0'
#8100000
b10100 &
b10100 *
b10100 0
1'
#8200000
0'
#8300000
b10001001001100101101011000010010 )
b10001001001100101101011000010010 +
1'
#8400000
0'
#8500000
b10101 &
b10101 *
b10101 0
1'
#8600000
0'
#8700000
b1000111111011001101101110001111 )
b1000111111011001101101110001111 +
1'
#8800000
0'
#8900000
b10110 &
b10110 *
b10110 0
1'
#9000000
0'
#9100000
b1111001001100000110100111110010 )
b1111001001100000110100111110010 +
1'
#9200000
0'
#9300000
b10111 &
b10111 *
b10111 0
1'
#9400000
0'
#9500000
b11100111011101101001011011001110 )
b11100111011101101001011011001110 +
1'
#9600000
0'
#9700000
b11000 &
b11000 *
b11000 0
1'
#9800000
0'
#9900000
b11110100000000000111101011101000 )
b11110100000000000111101011101000 +
1'
#10000000
0'
#10100000
b11001 &
b11001 *
b11001 0
1'
#10200000
0'
#10300000
b11100010110010100100111011000101 )
b11100010110010100100111011000101 +
1'
#10400000
0'
#10500000
b11010 &
b11010 *
b11010 0
1'
#10600000
0'
#10700000
b101110010110000100100101011100 )
b101110010110000100100101011100 +
1'
#10800000
0'
#10900000
b11011 &
b11011 *
b11011 0
1'
#11000000
0'
#11100000
b11011110100011100010100010111101 )
b11011110100011100010100010111101 +
1'
#11200000
0'
#11300000
b11100 &
b11100 *
b11100 0
1'
#11400000
0'
#11500000
b10010110101010110101100000101101 )
b10010110101010110101100000101101 +
1'
#11600000
0'
#11700000
b11101 &
b11101 *
b11101 0
1'
#11800000
0'
#11900000
b10110010101001110010011001100101 )
b10110010101001110010011001100101 +
1'
#12000000
0'
#12100000
b11110 &
b11110 *
b11110 0
1'
#12200000
0'
#12300000
b10110001111011110110001001100011 )
b10110001111011110110001001100011 +
1'
#12400000
0'
#12500000
b11111 &
b11111 *
b11111 0
1'
#12600000
0'
#12700000
b101011100111000011100001010 )
b101011100111000011100001010 +
1'
#12800000
0'
#12900000
b0 &
b0 *
b0 1
0%
b100000 0
1'
#13000000
0'
#13100000
b10010000101010011010100100100 !
b10010000101010011010100100100 .
1$
1'
#13200000
0'
#13300000
b1 &
b1 *
b1 1
1'
#13400000
0'
#13500000
b11000000100010010101111010000001 !
b11000000100010010101111010000001 .
1'
#13600000
0'
#13700000
b10 &
b10 *
b10 1
1'
#13800000
0'
#13900000
b10000100100001001101011000001001 !
b10000100100001001101011000001001 .
1'
#14000000
0'
#14100000
b11 &
b11 *
b11 1
1'
#14200000
0'
#14300000
b10110001111100000101011001100011 !
b10110001111100000101011001100011 .
1'
#14400000
0'
#14500000
b100 &
b100 *
b100 1
1'
#14600000
0'
#14700000
b110101110010111101100001101 !
b110101110010111101100001101 .
1'
#14800000
0'
#14900000
b101 &
b101 *
b101 1
1'
#15000000
0'
#15100000
b1000110110111111001100110001101 !
b1000110110111111001100110001101 .
1'
#15200000
0'
#15300000
b110 &
b110 *
b110 1
1'
#15400000
0'
#15500000
b10110010110000101000010001100101 !
b10110010110000101000010001100101 .
1'
#15600000
0'
#15700000
b111 &
b111 *
b111 1
1'
#15800000
0'
#15900000
b10001001001101110101001000010010 !
b10001001001101110101001000010010 .
1'
#16000000
0'
#16100000
b1000 &
b1000 *
b1000 1
1'
#16200000
0'
#16300000
b111100111110001100000001 !
b111100111110001100000001 .
1'
#16400000
0'
#16500000
b1001 &
b1001 *
b1001 1
1'
#16600000
0'
#16700000
b110110101111100110100001101 !
b110110101111100110100001101 .
1'
#16800000
0'
#16900000
b1010 &
b1010 *
b1010 1
1'
#17000000
0'
#17100000
b111011001000111111000101110110 !
b111011001000111111000101110110 .
1'
#17200000
0'
#17300000
b1011 &
b1011 *
b1011 1
1'
#17400000
0'
#17500000
b11110100011011100110100111101 !
b11110100011011100110100111101 .
1'
#17600000
0'
#17700000
b1100 &
b1100 *
b1100 1
1'
#17800000
0'
#17900000
b1110110110101000101011111101101 !
b1110110110101000101011111101101 .
1'
#18000000
0'
#18100000
b1101 &
b1101 *
b1101 1
1'
#18200000
0'
#18300000
b1000110001011011111011110001100 !
b1000110001011011111011110001100 .
1'
#18400000
0'
#18500000
b1110 &
b1110 *
b1110 1
1'
#18600000
0'
#18700000
b1111100111111011110100111111001 !
b1111100111111011110100111111001 .
1'
#18800000
0'
#18900000
b1111 &
b1111 *
b1111 1
1'
#19000000
0'
#19100000
b11100011001101110010010011000110 !
b11100011001101110010010011000110 .
1'
#19200000
0'
#19300000
b10000 &
b10000 *
b10000 1
1'
#19400000
0'
#19500000
b11100010111101111000010011000101 !
b11100010111101111000010011000101 .
1'
#19600000
0'
#19700000
b10001 &
b10001 *
b10001 1
1'
#19800000
0'
#19900000
b11010101000100111101001010101010 !
b11010101000100111101001010101010 .
1'
#20000000
0'
#20100000
b10010 &
b10010 *
b10010 1
1'
#20200000
0'
#20300000
b1110010101011111111011111100101 !
b1110010101011111111011111100101 .
1'
#20400000
0'
#20500000
b10011 &
b10011 *
b10011 1
1'
#20600000
0'
#20700000
b10111011110100100111001001110111 !
b10111011110100100111001001110111 .
1'
#20800000
0'
#20900000
b10100 &
b10100 *
b10100 1
1'
#21000000
0'
#21100000
b10001001001100101101011000010010 !
b10001001001100101101011000010010 .
1'
#21200000
0'
#21300000
b10101 &
b10101 *
b10101 1
1'
#21400000
0'
#21500000
b1000111111011001101101110001111 !
b1000111111011001101101110001111 .
1'
#21600000
0'
#21700000
b10110 &
b10110 *
b10110 1
1'
#21800000
0'
#21900000
b1111001001100000110100111110010 !
b1111001001100000110100111110010 .
1'
#22000000
0'
#22100000
b10111 &
b10111 *
b10111 1
1'
#22200000
0'
#22300000
b11100111011101101001011011001110 !
b11100111011101101001011011001110 .
1'
#22400000
0'
#22500000
b11000 &
b11000 *
b11000 1
1'
#22600000
0'
#22700000
b11110100000000000111101011101000 !
b11110100000000000111101011101000 .
1'
#22800000
0'
#22900000
b11001 &
b11001 *
b11001 1
1'
#23000000
0'
#23100000
b11100010110010100100111011000101 !
b11100010110010100100111011000101 .
1'
#23200000
0'
#23300000
b11010 &
b11010 *
b11010 1
1'
#23400000
0'
#23500000
b101110010110000100100101011100 !
b101110010110000100100101011100 .
1'
#23600000
0'
#23700000
b11011 &
b11011 *
b11011 1
1'
#23800000
0'
#23900000
b11011110100011100010100010111101 !
b11011110100011100010100010111101 .
1'
#24000000
0'
#24100000
b11100 &
b11100 *
b11100 1
1'
#24200000
0'
#24300000
b10010110101010110101100000101101 !
b10010110101010110101100000101101 .
1'
#24400000
0'
#24500000
b11101 &
b11101 *
b11101 1
1'
#24600000
0'
#24700000
b10110010101001110010011001100101 !
b10110010101001110010011001100101 .
1'
#24800000
0'
#24900000
b11110 &
b11110 *
b11110 1
1'
#25000000
0'
#25100000
b10110001111011110110001001100011 !
b10110001111011110110001001100011 .
1'
#25200000
0'
#25300000
b11111 &
b11111 *
b11111 1
1'
#25400000
0'
#25500000
b101011100111000011100001010 !
b101011100111000011100001010 .
1'
#25600000
0'
#25700000
b100000 1
1'
