data_memory/data_memory.sv
module data_memory #(
parameter W = 32,
parameter N=5
)(
    input logic clk,

    input logic [N-1:0] address, //direcición de 'consulta 1'
    input logic rst,
    input logic MemRead, //habilitación de lectura
    input logic MemWrite, //habilitación de escritura
    input logic [W-1:0] write_data, //valor de almacenamiento
    
    //a la salida mostramos el contenido de la memoria
    output logic [W-1:0] read_data
);
//creamos propiamente el registro: 
reg  [W-1:0] mem[(2**N)-1:0] ;


always_ff @(posedge clk) begin
    if (rst) begin
        foreach (mem[i])begin
            mem[i] <= 0;
        end
        read_data <= 0;
    end
    else begin
    if (MemWrite) mem[address]<=write_data;
    if (MemRead) read_data <= mem[address];
    end
end

endmodule

data_memory/data_memory_tb.sv
`timescale 100ns / 1ps
module data_memory_tb;

    // Parámetros del módulo
    parameter W = 32;
    parameter N = 5;
    
    // Definición de señales
    logic clk;
    logic [N-1:0] address;
    logic [W-1:0] write_data;
    logic [W-1:0] read_data; 
    logic MemRead;
    logic MemWrite;
    logic rst;

    // Instancia del módulo bajo prueba
    data_memory #(W, N) dut (
        .rst(rst),
        .clk(clk),
        .address(address),
        .MemWrite(MemWrite),
        .MemRead(MemRead),
        .write_data(write_data),
        .read_data(read_data)
    );

    // Generación de clock a 1 kHz
    always #1 clk = ~clk;

    initial begin
        $dumpfile("data_memory.vcd");
        $dumpvars(0, data_memory_tb);
    end

    // Test case: Escribir en todas dlas posibles direcciones y verificar
    initial begin
        rst = 1;
        clk = 0;
        @(posedge clk); // Esperar un poco para estabilizar la simulación
        rst <= 0;

        // Escribir datos en todas las posibles direcciones de memoria
        for (integer i = 0; i < (1 << N); i++) begin
            address = i; // Dirección de memoria
            write_data = $random; // Datos aleatorios a escribir
            MemWrite = 1; // Habilitación de escritura
            #10;
        end
        MemWrite = 0;
        
        // Leer datos de todas las direcciones de memoria y verificar si son correctos
        for (integer i = 0; i < (1 << N); i++) begin
            address = i; // Dirección de memoria
            MemRead = 1;
            #10;
            if (read_data !== dut.mem[i+1]) begin
                $display("Test case failed at address %d", i);
            end else begin
                $display("Mem %0d: %h", i, read_data);
                end
        end
        #10; // Esperar un poco al final antes de finalizar la simulación
        $finish; // Finalizar la simulación
    end

endmodule

data_memory/data_memory.vcd
$date
	Wed Apr 03 16:15:09 2024
$end
$version
	Icarus Verilog
$end
$timescale
	1ps
$end
$scope module data_memory_tb $end
$var wire 32 ! read_data [31:0] $end
$var parameter 32 " N $end
$var parameter 32 # W $end
$var reg 1 $ MemRead $end
$var reg 1 % MemWrite $end
$var reg 5 & address [4:0] $end
$var reg 1 ' clk $end
$var reg 1 ( rst $end
$var reg 32 ) write_data [31:0] $end
$scope module dut $end
$var wire 1 $ MemRead $end
$var wire 1 % MemWrite $end
$var wire 5 * address [4:0] $end
$var wire 1 ' clk $end
$var wire 1 ( rst $end
$var wire 32 + write_data [31:0] $end
$var parameter 32 , N $end
$var parameter 32 - W $end
$var reg 32 . read_data [31:0] $end
$scope begin $ivl_foreach0 $end
$var integer 32 / i [31:0] $end
$upscope $end
$upscope $end
$scope begin $ivl_for_loop0 $end
$var integer 32 0 i [31:0] $end
$upscope $end
$scope begin $ivl_for_loop1 $end
$var integer 32 1 i [31:0] $end
$upscope $end
$upscope $end
$enddefinitions $end
$comment Show the parameter values. $end
$dumpall
b100000 -
b101 ,
b100000 #
b101 "
$end
#0
$dumpvars
bx 1
bx 0
b0 /
bx .
bx +
bx *
bx )
1(
0'
bx &
x%
x$
bx !
$end
#100000
b0 !
b0 .
0(
1%
b10010000101010011010100100100 )
b10010000101010011010100100100 +
b0 &
b0 *
b0 0
b100000 /
1'
#200000
0'
#300000
1'
#400000
0'
#500000
1'
#600000
0'
#700000
1'
#800000
0'
#900000
1'
#1000000
0'
#1100000
1'
b11000000100010010101111010000001 )
b11000000100010010101111010000001 +
b1 &
b1 *
b1 0
#1200000
0'
#1300000
1'
#1400000
0'
#1500000
1'
#1600000
0'
#1700000
1'
#1800000
0'
#1900000
1'
#2000000
0'
#2100000
1'
b10000100100001001101011000001001 )
b10000100100001001101011000001001 +
b10 &
b10 *
b10 0
#2200000
0'
#2300000
1'
#2400000
0'
#2500000
1'
#2600000
0'
#2700000
1'
#2800000
0'
#2900000
1'
#3000000
0'
#3100000
1'
b10110001111100000101011001100011 )
b10110001111100000101011001100011 +
b11 &
b11 *
b11 0
#3200000
0'
#3300000
1'
#3400000
0'
#3500000
1'
#3600000
0'
#3700000
1'
#3800000
0'
#3900000
1'
#4000000
0'
#4100000
1'
b110101110010111101100001101 )
b110101110010111101100001101 +
b100 &
b100 *
b100 0
#4200000
0'
#4300000
1'
#4400000
0'
#4500000
1'
#4600000
0'
#4700000
1'
#4800000
0'
#4900000
1'
#5000000
0'
#5100000
1'
b1000110110111111001100110001101 )
b1000110110111111001100110001101 +
b101 &
b101 *
b101 0
#5200000
0'
#5300000
1'
#5400000
0'
#5500000
1'
#5600000
0'
#5700000
1'
#5800000
0'
#5900000
1'
#6000000
0'
#6100000
1'
b10110010110000101000010001100101 )
b10110010110000101000010001100101 +
b110 &
b110 *
b110 0
#6200000
0'
#6300000
1'
#6400000
0'
#6500000
1'
#6600000
0'
#6700000
1'
#6800000
0'
#6900000
1'
#7000000
0'
#7100000
1'
b10001001001101110101001000010010 )
b10001001001101110101001000010010 +
b111 &
b111 *
b111 0
#7200000
0'
#7300000
1'
#7400000
0'
#7500000
1'
#7600000
0'
#7700000
1'
#7800000
0'
#7900000
1'
#8000000
0'
#8100000
1'
b111100111110001100000001 )
b111100111110001100000001 +
b1000 &
b1000 *
b1000 0
#8200000
0'
#8300000
1'
#8400000
0'
#8500000
1'
#8600000
0'
#8700000
1'
#8800000
0'
#8900000
1'
#9000000
0'
#9100000
1'
b110110101111100110100001101 )
b110110101111100110100001101 +
b1001 &
b1001 *
b1001 0
#9200000
0'
#9300000
1'
#9400000
0'
#9500000
1'
#9600000
0'
#9700000
1'
#9800000
0'
#9900000
1'
#10000000
0'
#10100000
1'
b111011001000111111000101110110 )
b111011001000111111000101110110 +
b1010 &
b1010 *
b1010 0
#10200000
0'
#10300000
1'
#10400000
0'
#10500000
1'
#10600000
0'
#10700000
1'
#10800000
0'
#10900000
1'
#11000000
0'
#11100000
1'
b11110100011011100110100111101 )
b11110100011011100110100111101 +
b1011 &
b1011 *
b1011 0
#11200000
0'
#11300000
1'
#11400000
0'
#11500000
1'
#11600000
0'
#11700000
1'
#11800000
0'
#11900000
1'
#12000000
0'
#12100000
1'
b1110110110101000101011111101101 )
b1110110110101000101011111101101 +
b1100 &
b1100 *
b1100 0
#12200000
0'
#12300000
1'
#12400000
0'
#12500000
1'
#12600000
0'
#12700000
1'
#12800000
0'
#12900000
1'
#13000000
0'
#13100000
1'
b1000110001011011111011110001100 )
b1000110001011011111011110001100 +
b1101 &
b1101 *
b1101 0
#13200000
0'
#13300000
1'
#13400000
0'
#13500000
1'
#13600000
0'
#13700000
1'
#13800000
0'
#13900000
1'
#14000000
0'
#14100000
1'
b1111100111111011110100111111001 )
b1111100111111011110100111111001 +
b1110 &
b1110 *
b1110 0
#14200000
0'
#14300000
1'
#14400000
0'
#14500000
1'
#14600000
0'
#14700000
1'
#14800000
0'
#14900000
1'
#15000000
0'
#15100000
1'
b11100011001101110010010011000110 )
b11100011001101110010010011000110 +
b1111 &
b1111 *
b1111 0
#15200000
0'
#15300000
1'
#15400000
0'
#15500000
1'
#15600000
0'
#15700000
1'
#15800000
0'
#15900000
1'
#16000000
0'
#16100000
1'
b11100010111101111000010011000101 )
b11100010111101111000010011000101 +
b10000 &
b10000 *
b10000 0
#16200000
0'
#16300000
1'
#16400000
0'
#16500000
1'
#16600000
0'
#16700000
1'
#16800000
0'
#16900000
1'
#17000000
0'
#17100000
1'
b11010101000100111101001010101010 )
b11010101000100111101001010101010 +
b10001 &
b10001 *
b10001 0
#17200000
0'
#17300000
1'
#17400000
0'
#17500000
1'
#17600000
0'
#17700000
1'
#17800000
0'
#17900000
1'
#18000000
0'
#18100000
1'
b1110010101011111111011111100101 )
b1110010101011111111011111100101 +
b10010 &
b10010 *
b10010 0
#18200000
0'
#18300000
1'
#18400000
0'
#18500000
1'
#18600000
0'
#18700000
1'
#18800000
0'
#18900000
1'
#19000000
0'
#19100000
1'
b10111011110100100111001001110111 )
b10111011110100100111001001110111 +
b10011 &
b10011 *
b10011 0
#19200000
0'
#19300000
1'
#19400000
0'
#19500000
1'
#19600000
0'
#19700000
1'
#19800000
0'
#19900000
1'
#20000000
0'
#20100000
1'
b10001001001100101101011000010010 )
b10001001001100101101011000010010 +
b10100 &
b10100 *
b10100 0
#20200000
0'
#20300000
1'
#20400000
0'
#20500000
1'
#20600000
0'
#20700000
1'
#20800000
0'
#20900000
1'
#21000000
0'
#21100000
1'
b1000111111011001101101110001111 )
b1000111111011001101101110001111 +
b10101 &
b10101 *
b10101 0
#21200000
0'
#21300000
1'
#21400000
0'
#21500000
1'
#21600000
0'
#21700000
1'
#21800000
0'
#21900000
1'
#22000000
0'
#22100000
1'
b1111001001100000110100111110010 )
b1111001001100000110100111110010 +
b10110 &
b10110 *
b10110 0
#22200000
0'
#22300000
1'
#22400000
0'
#22500000
1'
#22600000
0'
#22700000
1'
#22800000
0'
#22900000
1'
#23000000
0'
#23100000
1'
b11100111011101101001011011001110 )
b11100111011101101001011011001110 +
b10111 &
b10111 *
b10111 0
#23200000
0'
#23300000
1'
#23400000
0'
#23500000
1'
#23600000
0'
#23700000
1'
#23800000
0'
#23900000
1'
#24000000
0'
#24100000
1'
b11110100000000000111101011101000 )
b11110100000000000111101011101000 +
b11000 &
b11000 *
b11000 0
#24200000
0'
#24300000
1'
#24400000
0'
#24500000
1'
#24600000
0'
#24700000
1'
#24800000
0'
#24900000
1'
#25000000
0'
#25100000
1'
b11100010110010100100111011000101 )
b11100010110010100100111011000101 +
b11001 &
b11001 *
b11001 0
#25200000
0'
#25300000
1'
#25400000
0'
#25500000
1'
#25600000
0'
#25700000
1'
#25800000
0'
#25900000
1'
#26000000
0'
#26100000
1'
b101110010110000100100101011100 )
b101110010110000100100101011100 +
b11010 &
b11010 *
b11010 0
#26200000
0'
#26300000
1'
#26400000
0'
#26500000
1'
#26600000
0'
#26700000
1'
#26800000
0'
#26900000
1'
#27000000
0'
#27100000
1'
b11011110100011100010100010111101 )
b11011110100011100010100010111101 +
b11011 &
b11011 *
b11011 0
#27200000
0'
#27300000
1'
#27400000
0'
#27500000
1'
#27600000
0'
#27700000
1'
#27800000
0'
#27900000
1'
#28000000
0'
#28100000
1'
b10010110101010110101100000101101 )
b10010110101010110101100000101101 +
b11100 &
b11100 *
b11100 0
#28200000
0'
#28300000
1'
#28400000
0'
#28500000
1'
#28600000
0'
#28700000
1'
#28800000
0'
#28900000
1'
#29000000
0'
#29100000
1'
b10110010101001110010011001100101 )
b10110010101001110010011001100101 +
b11101 &
b11101 *
b11101 0
#29200000
0'
#29300000
1'
#29400000
0'
#29500000
1'
#29600000
0'
#29700000
1'
#29800000
0'
#29900000
1'
#30000000
0'
#30100000
1'
b10110001111011110110001001100011 )
b10110001111011110110001001100011 +
b11110 &
b11110 *
b11110 0
#30200000
0'
#30300000
1'
#30400000
0'
#30500000
1'
#30600000
0'
#30700000
1'
#30800000
0'
#30900000
1'
#31000000
0'
#31100000
1'
b101011100111000011100001010 )
b101011100111000011100001010 +
b11111 &
b11111 *
b11111 0
#31200000
0'
#31300000
1'
#31400000
0'
#31500000
1'
#31600000
0'
#31700000
1'
#31800000
0'
#31900000
1'
#32000000
0'
#32100000
b10010000101010011010100100100 !
b10010000101010011010100100100 .
1'
1$
b0 &
b0 *
b0 1
0%
b100000 0
#32200000
0'
#32300000
1'
#32400000
0'
#32500000
1'
#32600000
0'
#32700000
1'
#32800000
0'
#32900000
1'
#33000000
0'
#33100000
b11000000100010010101111010000001 !
b11000000100010010101111010000001 .
1'
b1 &
b1 *
b1 1
#33200000
0'
#33300000
1'
#33400000
0'
#33500000
1'
#33600000
0'
#33700000
1'
#33800000
0'
#33900000
1'
#34000000
0'
#34100000
b10000100100001001101011000001001 !
b10000100100001001101011000001001 .
1'
b10 &
b10 *
b10 1
#34200000
0'
#34300000
1'
#34400000
0'
#34500000
1'
#34600000
0'
#34700000
1'
#34800000
0'
#34900000
1'
#35000000
0'
#35100000
b10110001111100000101011001100011 !
b10110001111100000101011001100011 .
1'
b11 &
b11 *
b11 1
#35200000
0'
#35300000
1'
#35400000
0'
#35500000
1'
#35600000
0'
#35700000
1'
#35800000
0'
#35900000
1'
#36000000
0'
#36100000
b110101110010111101100001101 !
b110101110010111101100001101 .
1'
b100 &
b100 *
b100 1
#36200000
0'
#36300000
1'
#36400000
0'
#36500000
1'
#36600000
0'
#36700000
1'
#36800000
0'
#36900000
1'
#37000000
0'
#37100000
b1000110110111111001100110001101 !
b1000110110111111001100110001101 .
1'
b101 &
b101 *
b101 1
#37200000
0'
#37300000
1'
#37400000
0'
#37500000
1'
#37600000
0'
#37700000
1'
#37800000
0'
#37900000
1'
#38000000
0'
#38100000
b10110010110000101000010001100101 !
b10110010110000101000010001100101 .
1'
b110 &
b110 *
b110 1
#38200000
0'
#38300000
1'
#38400000
0'
#38500000
1'
#38600000
0'
#38700000
1'
#38800000
0'
#38900000
1'
#39000000
0'
#39100000
b10001001001101110101001000010010 !
b10001001001101110101001000010010 .
1'
b111 &
b111 *
b111 1
#39200000
0'
#39300000
1'
#39400000
0'
#39500000
1'
#39600000
0'
#39700000
1'
#39800000
0'
#39900000
1'
#40000000
0'
#40100000
b111100111110001100000001 !
b111100111110001100000001 .
1'
b1000 &
b1000 *
b1000 1
#40200000
0'
#40300000
1'
#40400000
0'
#40500000
1'
#40600000
0'
#40700000
1'
#40800000
0'
#40900000
1'
#41000000
0'
#41100000
b110110101111100110100001101 !
b110110101111100110100001101 .
1'
b1001 &
b1001 *
b1001 1
#41200000
0'
#41300000
1'
#41400000
0'
#41500000
1'
#41600000
0'
#41700000
1'
#41800000
0'
#41900000
1'
#42000000
0'
#42100000
b111011001000111111000101110110 !
b111011001000111111000101110110 .
1'
b1010 &
b1010 *
b1010 1
#42200000
0'
#42300000
1'
#42400000
0'
#42500000
1'
#42600000
0'
#42700000
1'
#42800000
0'
#42900000
1'
#43000000
0'
#43100000
b11110100011011100110100111101 !
b11110100011011100110100111101 .
1'
b1011 &
b1011 *
b1011 1
#43200000
0'
#43300000
1'
#43400000
0'
#43500000
1'
#43600000
0'
#43700000
1'
#43800000
0'
#43900000
1'
#44000000
0'
#44100000
b1110110110101000101011111101101 !
b1110110110101000101011111101101 .
1'
b1100 &
b1100 *
b1100 1
#44200000
0'
#44300000
1'
#44400000
0'
#44500000
1'
#44600000
0'
#44700000
1'
#44800000
0'
#44900000
1'
#45000000
0'
#45100000
b1000110001011011111011110001100 !
b1000110001011011111011110001100 .
1'
b1101 &
b1101 *
b1101 1
#45200000
0'
#45300000
1'
#45400000
0'
#45500000
1'
#45600000
0'
#45700000
1'
#45800000
0'
#45900000
1'
#46000000
0'
#46100000
b1111100111111011110100111111001 !
b1111100111111011110100111111001 .
1'
b1110 &
b1110 *
b1110 1
#46200000
0'
#46300000
1'
#46400000
0'
#46500000
1'
#46600000
0'
#46700000
1'
#46800000
0'
#46900000
1'
#47000000
0'
#47100000
b11100011001101110010010011000110 !
b11100011001101110010010011000110 .
1'
b1111 &
b1111 *
b1111 1
#47200000
0'
#47300000
1'
#47400000
0'
#47500000
1'
#47600000
0'
#47700000
1'
#47800000
0'
#47900000
1'
#48000000
0'
#48100000
b11100010111101111000010011000101 !
b11100010111101111000010011000101 .
1'
b10000 &
b10000 *
b10000 1
#48200000
0'
#48300000
1'
#48400000
0'
#48500000
1'
#48600000
0'
#48700000
1'
#48800000
0'
#48900000
1'
#49000000
0'
#49100000
b11010101000100111101001010101010 !
b11010101000100111101001010101010 .
1'
b10001 &
b10001 *
b10001 1
#49200000
0'
#49300000
1'
#49400000
0'
#49500000
1'
#49600000
0'
#49700000
1'
#49800000
0'
#49900000
1'
#50000000
0'
#50100000
b1110010101011111111011111100101 !
b1110010101011111111011111100101 .
1'
b10010 &
b10010 *
b10010 1
#50200000
0'
#50300000
1'
#50400000
0'
#50500000
1'
#50600000
0'
#50700000
1'
#50800000
0'
#50900000
1'
#51000000
0'
#51100000
b10111011110100100111001001110111 !
b10111011110100100111001001110111 .
1'
b10011 &
b10011 *
b10011 1
#51200000
0'
#51300000
1'
#51400000
0'
#51500000
1'
#51600000
0'
#51700000
1'
#51800000
0'
#51900000
1'
#52000000
0'
#52100000
b10001001001100101101011000010010 !
b10001001001100101101011000010010 .
1'
b10100 &
b10100 *
b10100 1
#52200000
0'
#52300000
1'
#52400000
0'
#52500000
1'
#52600000
0'
#52700000
1'
#52800000
0'
#52900000
1'
#53000000
0'
#53100000
b1000111111011001101101110001111 !
b1000111111011001101101110001111 .
1'
b10101 &
b10101 *
b10101 1
#53200000
0'
#53300000
1'
#53400000
0'
#53500000
1'
#53600000
0'
#53700000
1'
#53800000
0'
#53900000
1'
#54000000
0'
#54100000
b1111001001100000110100111110010 !
b1111001001100000110100111110010 .
1'
b10110 &
b10110 *
b10110 1
#54200000
0'
#54300000
1'
#54400000
0'
#54500000
1'
#54600000
0'
#54700000
1'
#54800000
0'
#54900000
1'
#55000000
0'
#55100000
b11100111011101101001011011001110 !
b11100111011101101001011011001110 .
1'
b10111 &
b10111 *
b10111 1
#55200000
0'
#55300000
1'
#55400000
0'
#55500000
1'
#55600000
0'
#55700000
1'
#55800000
0'
#55900000
1'
#56000000
0'
#56100000
b11110100000000000111101011101000 !
b11110100000000000111101011101000 .
1'
b11000 &
b11000 *
b11000 1
#56200000
0'
#56300000
1'
#56400000
0'
#56500000
1'
#56600000
0'
#56700000
1'
#56800000
0'
#56900000
1'
#57000000
0'
#57100000
b11100010110010100100111011000101 !
b11100010110010100100111011000101 .
1'
b11001 &
b11001 *
b11001 1
#57200000
0'
#57300000
1'
#57400000
0'
#57500000
1'
#57600000
0'
#57700000
1'
#57800000
0'
#57900000
1'
#58000000
0'
#58100000
b101110010110000100100101011100 !
b101110010110000100100101011100 .
1'
b11010 &
b11010 *
b11010 1
#58200000
0'
#58300000
1'
#58400000
0'
#58500000
1'
#58600000
0'
#58700000
1'
#58800000
0'
#58900000
1'
#59000000
0'
#59100000
b11011110100011100010100010111101 !
b11011110100011100010100010111101 .
1'
b11011 &
b11011 *
b11011 1
#59200000
0'
#59300000
1'
#59400000
0'
#59500000
1'
#59600000
0'
#59700000
1'
#59800000
0'
#59900000
1'
#60000000
0'
#60100000
b10010110101010110101100000101101 !
b10010110101010110101100000101101 .
1'
b11100 &
b11100 *
b11100 1
#60200000
0'
#60300000
1'
#60400000
0'
#60500000
1'
#60600000
0'
#60700000
1'
#60800000
0'
#60900000
1'
#61000000
0'
#61100000
b10110010101001110010011001100101 !
b10110010101001110010011001100101 .
1'
b11101 &
b11101 *
b11101 1
#61200000
0'
#61300000
1'
#61400000
0'
#61500000
1'
#61600000
0'
#61700000
1'
#61800000
0'
#61900000
1'
#62000000
0'
#62100000
b10110001111011110110001001100011 !
b10110001111011110110001001100011 .
1'
b11110 &
b11110 *
b11110 1
#62200000
0'
#62300000
1'
#62400000
0'
#62500000
1'
#62600000
0'
#62700000
1'
#62800000
0'
#62900000
1'
#63000000
0'
#63100000
b101011100111000011100001010 !
b101011100111000011100001010 .
1'
b11111 &
b11111 *
b11111 1
#63200000
0'
#63300000
1'
#63400000
0'
#63500000
1'
#63600000
0'
#63700000
1'
#63800000
0'
#63900000
1'
#64000000
0'
#64100000
1'
b100000 1
