data_memory/data_memory.sv
module data_memory #(
parameter W = 32,
parameter N=5
)(
    input logic clk,

    input logic [N-1:0] address, //direcición de 'consulta 1'
    input logic rst,
    input logic MemRead, //habilitación de lectura
    input logic MemWrite, //habilitación de escritura
    input logic [W-1:0] write_data, //valor de almacenamiento
    
    //a la salida mostramos el contenido de la memoria
    output logic [W-1:0] read_data
);
//creamos propiamente el registro: 
reg  [W-1:0] mem[(2**N)-1:0] ;


always_ff @(posedge clk) begin
    if (rst) begin
        foreach (mem[i])begin
            mem[i] <= 0;
        end
        read_data <= 0;
    end
    else begin
    if (MemWrite) mem[address]<=write_data;
    if (MemRead) read_data <= mem[address];
    end
end

endmodule

data_memory/data_memory_tb.sv
`timescale 100ns / 1ps
module data_memory_tb;

    // Parámetros del módulo
    parameter W = 32;
    parameter N = 5;
    
    // Definición de señales
    logic clk;
    logic [W-1:0] address;
    logic [W-1:0] write_data;
    logic [W-1:0] read_data; 
    logic MemRead;
    logic MemWrite;
    logic rst;

    // Instancia del módulo bajo prueba
    data_memory #(W, N) dut (
        .rst(rst),
        .clk(clk),
        .address(address),
        .MemWrite(MemWrite),
        .MemRead(MemRead),
        .write_data(write_data),
        .read_data(read_data)
    );

    // Generación de clock a 1 kHz
    always #1 clk = ~clk;

    initial begin
        $dumpfile("data_memory.vcd");
        $dumpvars(0, data_memory_tb);
    end

    // Test case: Escribir en todas dlas posibles direcciones y verificar
    initial begin
        rst = 1;
        clk = 0;
        MemRead = 1;
        @(posedge clk); // Esperar un poco para estabilizar la simulación
        rst <= 0;

        // Escribir datos en todas las posibles direcciones de memoria
        // for (integer i = 0; i < (1 << N); i++) begin
        //     address = i; // Dirección de memoria
        //     @(posedge clk);
        //     write_data = $random; // Datos aleatorios a escribir
        //     MemWrite = 1; // Habilitación de escritura
        //     @(posedge clk);
        // end
        // MemWrite = 0;
        
        // Leer datos de todas las direcciones de memoria y verificar si son correctos
        for (integer i = 0; i < (1 << N); i=i+4) begin
            address = i; // Dirección de memoria
            @(posedge clk);
            
            // @(posedge clk);
            // if (read_data !== dut.mem[i]) begin
            //     $display("Test case failed at address %d", i);
            // end else begin
            //     $display("Mem %0d: %h", i, read_data);
            //     end
        end
        @(posedge clk); // Esperar un poco al final antes de finalizar la simulación
        $finish; // Finalizar la simulación
    end

endmodule

data_memory/data_memory.vcd
$date
	Thu Apr 11 18:10:26 2024
$end
$version
	Icarus Verilog
$end
$timescale
	1ps
$end
$scope module data_memory_tb $end
$var wire 32 ! read_data [31:0] $end
$var parameter 32 " N $end
$var parameter 32 # W $end
$var reg 1 $ MemRead $end
$var reg 1 % MemWrite $end
$var reg 32 & address [31:0] $end
$var reg 1 ' clk $end
$var reg 1 ( rst $end
$var reg 32 ) write_data [31:0] $end
$scope module dut $end
$var wire 1 $ MemRead $end
$var wire 1 % MemWrite $end
$var wire 32 * address [31:0] $end
$var wire 1 ' clk $end
$var wire 1 ( rst $end
$var wire 32 + write_data [31:0] $end
$var wire 32 , read_data [31:0] $end
$var parameter 32 - N $end
$var parameter 32 . W $end
$upscope $end
$scope begin $ivl_for_loop0 $end
$var integer 32 / i [31:0] $end
$upscope $end
$upscope $end
$enddefinitions $end
$comment Show the parameter values. $end
$dumpall
b100000 .
b101 -
b100000 #
b101 "
$end
#0
$dumpvars
bx /
b0 ,
bx +
bx *
bx )
1(
0'
bx &
x%
1$
b0 !
$end
#100000
b101000000000010100010011 !
b101000000000010100010011 ,
0(
b0 &
b0 *
b0 /
1'
#200000
0'
#300000
b101100000000010110010011 !
b101100000000010110010011 ,
b100 &
b100 *
b100 /
1'
#400000
0'
#500000
b101001011000011000110011 !
b101001011000011000110011 ,
b1000 &
b1000 *
b1000 /
1'
#600000
0'
#700000
b110000010010010000100011 !
b110000010010010000100011 ,
b1100 &
b1100 *
b1100 /
1'
#800000
0'
#900000
b100000010010011010000011 !
b100000010010011010000011 ,
b10000 &
b10000 *
b10000 /
1'
#1000000
0'
#1100000
bx !
bx ,
b10100 &
b10100 *
b10100 /
1'
#1200000
0'
#1300000
b11000 &
b11000 *
b11000 /
1'
#1400000
0'
#1500000
b11100 &
b11100 *
b11100 /
1'
#1600000
0'
#1700000
b100000 /
1'
