data_memory/data_memory.sv
module data_memory #(
parameter W = 32,
parameter N=5
)(
    input logic clk,

    input logic [N-1:0] address, //direcición de 'consulta 1'
    input logic rst,
    input logic MemRead, //habilitación de lectura
    input logic MemWrite, //habilitación de escritura
    input logic [W-1:0] write_data, //valor de almacenamiento
    
    //a la salida mostramos el contenido de la memoria
    output logic [W-1:0] read_data
);
//creamos propiamente el registro: 
reg  [W-1:0] mem[(2**N)-1:0] ;


always_ff @(posedge clk) begin
    if (rst) begin
        foreach (mem[i])begin
            mem[i] <= 0;
        end
        read_data <= 0;
    end
    else begin
    if (MemWrite) mem[address]<=write_data;
    if (MemRead) read_data <= mem[address];
    end
end

endmodule

test/data_memory_tb.sv
`timescale 1ns / 1ns

module data_memory_tb;

parameter W = 32;
parameter N = 5;

         

logic [W-1:0] wrt_data;      //dato a almacenar

logic [W-1:0] rd_data;

logic [N-1:0] addr;

logic clk;
logic rst;

logic memread;
logic memwrite;

integer i;

data_memory #(.W(W), .N(N)) dut (
    .clk(clk),
    .rst(rst),
    .MemRead(memread),
    .MemWrite(memwrite),
    .write_data(wrt_data),
    .read_data(rd_data),
    .address(addr)
);
initial forever begin
clk=~clk;
#1;
end
initial begin
clk=0;
rst=1;
#10;
rst=0;


memread=0;
memwrite=0;

wrt_data=0;
addr=0;

for (i = 0;i<N ;i=i+1 ) begin
    memwrite = 1'b1;
    addr=i;
    
    #10;
    wrt_data=$urandom_range(W);
    #10;                //guarda el dato random
    memwrite = 1'b0;
    #10
    memread = 1'b1;
    #10;
    $display("Operand1 = %b", rd_data);     //muestra el dato random guardado
    #10;
    memread = 1'b0;

end

$finish;

end



endmodule

data_memory/data_memory.vcd
$date
	Wed Apr 10 16:43:32 2024
$end

$version
	Synopsys VCS version R-2020.12-SP2_Full64
$end

$timescale
	1ps
$end

$comment Csum: 1 614b8af901d75872 $end


$scope module data_memory_tb $end
$var reg 1 ! clk $end
$var reg 5 " address [4:0] $end
$var reg 32 # write_data [31:0] $end
$var reg 32 $ read_data [31:0] $end
$var reg 1 % MemRead $end
$var reg 1 & MemWrite $end
$var reg 1 ' rst $end

$scope begin unnamed$$_0 $end
$upscope $end


$scope begin unnamed$$_1 $end
$upscope $end


$scope module dut $end
$var reg 1 ! clk $end
$var reg 5 " address [4:0] $end
$var reg 1 ' rst $end
$var reg 1 % MemRead $end
$var reg 1 & MemWrite $end
$var reg 32 # write_data [31:0] $end
$var reg 32 $ read_data [31:0] $end

$scope begin unnamed$$_0 $end
$upscope $end

$upscope $end

$upscope $end

$enddefinitions $end

#0
$dumpvars
x%
x&
0!
1'
bxxxxx "
bxxxxxxxxxxxxxxxxxxxxxxxxxxxxxxxx $
bxxxxxxxxxxxxxxxxxxxxxxxxxxxxxxxx #
$end
#100000
1!
b00000 "
0'
b00000000000000000000000000000000 $
#200000
0!
#300000
1!
b00010010000101010011010100100100 #
1&
#400000
0!
#500000
1!
b00001 "
#600000
0!
#700000
1!
b11000000100010010101111010000001 #
#800000
0!
#900000
1!
b00010 "
#1000000
0!
#1100000
1!
b10000100100001001101011000001001 #
#1200000
0!
#1300000
1!
b00011 "
#1400000
0!
#1500000
1!
b10110001111100000101011001100011 #
#1600000
0!
#1700000
1!
b00100 "
#1800000
0!
#1900000
1!
b00000110101110010111101100001101 #
#2000000
0!
#2100000
1!
b00101 "
#2200000
0!
#2300000
1!
b01000110110111111001100110001101 #
#2400000
0!
#2500000
1!
b00110 "
#2600000
0!
#2700000
1!
b10110010110000101000010001100101 #
#2800000
0!
#2900000
1!
b00111 "
#3000000
0!
#3100000
1!
b10001001001101110101001000010010 #
#3200000
0!
#3300000
1!
b01000 "
#3400000
0!
#3500000
1!
b00000000111100111110001100000001 #
#3600000
0!
#3700000
1!
b01001 "
#3800000
0!
#3900000
1!
b00000110110101111100110100001101 #
#4000000
0!
#4100000
1!
b01010 "
#4200000
0!
#4300000
1!
b00111011001000111111000101110110 #
#4400000
0!
#4500000
1!
b01011 "
#4600000
0!
#4700000
1!
b00011110100011011100110100111101 #
#4800000
0!
#4900000
1!
b01100 "
#5000000
0!
#5100000
1!
b01110110110101000101011111101101 #
#5200000
0!
#5300000
1!
b01101 "
#5400000
0!
#5500000
1!
b01000110001011011111011110001100 #
#5600000
0!
#5700000
1!
b01110 "
#5800000
0!
#5900000
1!
b01111100111111011110100111111001 #
#6000000
0!
#6100000
1!
b01111 "
#6200000
0!
#6300000
1!
b11100011001101110010010011000110 #
#6400000
0!
#6500000
1!
b10000 "
#6600000
0!
#6700000
1!
b11100010111101111000010011000101 #
#6800000
0!
#6900000
1!
b10001 "
#7000000
0!
#7100000
1!
b11010101000100111101001010101010 #
#7200000
0!
#7300000
1!
b10010 "
#7400000
0!
#7500000
1!
b01110010101011111111011111100101 #
#7600000
0!
#7700000
1!
b10011 "
#7800000
0!
#7900000
1!
b10111011110100100111001001110111 #
#8000000
0!
#8100000
1!
b10100 "
#8200000
0!
#8300000
1!
b10001001001100101101011000010010 #
#8400000
0!
#8500000
1!
b10101 "
#8600000
0!
#8700000
1!
b01000111111011001101101110001111 #
#8800000
0!
#8900000
1!
b10110 "
#9000000
0!
#9100000
1!
b01111001001100000110100111110010 #
#9200000
0!
#9300000
1!
b10111 "
#9400000
0!
#9500000
1!
b11100111011101101001011011001110 #
#9600000
0!
#9700000
1!
b11000 "
#9800000
0!
#9900000
1!
b11110100000000000111101011101000 #
#10000000
0!
#10100000
1!
b11001 "
#10200000
0!
#10300000
1!
b11100010110010100100111011000101 #
#10400000
0!
#10500000
1!
b11010 "
#10600000
0!
#10700000
1!
b00101110010110000100100101011100 #
#10800000
0!
#10900000
1!
b11011 "
#11000000
0!
#11100000
1!
b11011110100011100010100010111101 #
#11200000
0!
#11300000
1!
b11100 "
#11400000
0!
#11500000
1!
b10010110101010110101100000101101 #
#11600000
0!
#11700000
1!
b11101 "
#11800000
0!
#11900000
1!
b10110010101001110010011001100101 #
#12000000
0!
#12100000
1!
b11110 "
#12200000
0!
#12300000
1!
b10110001111011110110001001100011 #
#12400000
0!
#12500000
1!
b11111 "
#12600000
0!
#12700000
1!
b00000101011100111000011100001010 #
#12800000
0!
#12900000
1!
0&
b00000 "
#13000000
0!
#13100000
1!
1%
b00010010000101010011010100100100 $
#13200000
0!
#13300000
1!
b00001 "
b11000000100010010101111010000001 $
#13400000
0!
#13500000
1!
#13600000
0!
#13700000
1!
b00010 "
b10000100100001001101011000001001 $
#13800000
0!
#13900000
1!
#14000000
0!
#14100000
1!
b00011 "
b10110001111100000101011001100011 $
#14200000
0!
#14300000
1!
#14400000
0!
#14500000
1!
b00100 "
b00000110101110010111101100001101 $
#14600000
0!
#14700000
1!
#14800000
0!
#14900000
1!
b00101 "
b01000110110111111001100110001101 $
#15000000
0!
#15100000
1!
#15200000
0!
#15300000
1!
b00110 "
b10110010110000101000010001100101 $
#15400000
0!
#15500000
1!
#15600000
0!
#15700000
1!
b00111 "
b10001001001101110101001000010010 $
#15800000
0!
#15900000
1!
#16000000
0!
#16100000
1!
b01000 "
b00000000111100111110001100000001 $
#16200000
0!
#16300000
1!
#16400000
0!
#16500000
1!
b01001 "
b00000110110101111100110100001101 $
#16600000
0!
#16700000
1!
#16800000
0!
#16900000
1!
b01010 "
b00111011001000111111000101110110 $
#17000000
0!
#17100000
1!
#17200000
0!
#17300000
1!
b01011 "
b00011110100011011100110100111101 $
#17400000
0!
#17500000
1!
#17600000
0!
#17700000
1!
b01100 "
b01110110110101000101011111101101 $
#17800000
0!
#17900000
1!
#18000000
0!
#18100000
1!
b01101 "
b01000110001011011111011110001100 $
#18200000
0!
#18300000
1!
#18400000
0!
#18500000
1!
b01110 "
b01111100111111011110100111111001 $
#18600000
0!
#18700000
1!
#18800000
0!
#18900000
1!
b01111 "
b11100011001101110010010011000110 $
#19000000
0!
#19100000
1!
#19200000
0!
#19300000
1!
b10000 "
b11100010111101111000010011000101 $
#19400000
0!
#19500000
1!
#19600000
0!
#19700000
1!
b10001 "
b11010101000100111101001010101010 $
#19800000
0!
#19900000
1!
#20000000
0!
#20100000
1!
b10010 "
b01110010101011111111011111100101 $
#20200000
0!
#20300000
1!
#20400000
0!
#20500000
1!
b10011 "
b10111011110100100111001001110111 $
#20600000
0!
#20700000
1!
#20800000
0!
#20900000
1!
b10100 "
b10001001001100101101011000010010 $
#21000000
0!
#21100000
1!
#21200000
0!
#21300000
1!
b10101 "
b01000111111011001101101110001111 $
#21400000
0!
#21500000
1!
#21600000
0!
#21700000
1!
b10110 "
b01111001001100000110100111110010 $
#21800000
0!
#21900000
1!
#22000000
0!
#22100000
1!
b10111 "
b11100111011101101001011011001110 $
#22200000
0!
#22300000
1!
#22400000
0!
#22500000
1!
b11000 "
b11110100000000000111101011101000 $
#22600000
0!
#22700000
1!
#22800000
0!
#22900000
1!
b11001 "
b11100010110010100100111011000101 $
#23000000
0!
#23100000
1!
#23200000
0!
#23300000
1!
b11010 "
b00101110010110000100100101011100 $
#23400000
0!
#23500000
1!
#23600000
0!
#23700000
1!
b11011 "
b11011110100011100010100010111101 $
#23800000
0!
#23900000
1!
#24000000
0!
#24100000
1!
b11100 "
b10010110101010110101100000101101 $
#24200000
0!
#24300000
1!
#24400000
0!
#24500000
1!
b11101 "
b10110010101001110010011001100101 $
#24600000
0!
#24700000
1!
#24800000
0!
#24900000
1!
b11110 "
b10110001111011110110001001100011 $
#25000000
0!
#25100000
1!
#25200000
0!
#25300000
1!
b11111 "
b00000101011100111000011100001010 $
