design/ALU.sv
module ALU #(
    parameter DATA_WIDTH = 32
) (
    input logic [DATA_WIDTH-1:0] data_rs1,
    input logic [DATA_WIDTH-1:0] source_2,
    input logic [3:0] alu_inst,

    output logic [DATA_WIDTH-1:0] ALU_result,
    output logic zero
);
    
logic [DATA_WIDTH-1:0] ALUResult;

assign ALUResult = ALU_result;
    
always @ (*) begin
    if(ALUResult==0)begin
        zero = 1'b1;
    end else begin
         zero=1'b0;
    end
end


always @(*) begin
    case(alu_inst)

        4'b0010 : ALU_result = data_rs1 + source_2;  //suma
        4'b0110 : ALU_result = data_rs1 - source_2;  //resta
        4'b0000 : ALU_result = data_rs1 & source_2;  //AND
        4'b0001 : ALU_result = data_rs1 | source_2; //OR

        default ALU_result=data_rs1 + source_2;
endcase

end

endmodule

ALU/ALU_tb.sv
`timescale 1ns / 1ns

module ALU_tb;

// Parámetros
  parameter WIDTH = 5;  // Ancho de los operandos

  // Señales
  reg [WIDTH-1:0] operand1, operand2;
  reg [1:0] opcode;
  wire [WIDTH-1:0] result;
  wire zero_o;
 
  // Instancia de la ALU
  ALU #(.DATA_WIDTH(WIDTH)) alu_inst (
    .data_rs1(operand1),
    .source_2(operand2),
    .alu_inst(opcode),
    .ALU_result(result),
    .zero(zero_o)
  );
  integer i;
  // Generación de estímulos
 initial begin
    $dumpfile("ALU_tb.vcd"); // Especifica el nombre del archivo VCD
    $dumpvars(1, ALU_tb); // Define el alcance de la generación del VCD
 
     
    operand1 = 0;
    operand2 = 0;
    opcode = 0;
 

 for (i = 0 ;i<10 ;i=i+1 ) begin
    #10;
    if (i==0) begin
        operand1 = 5;
        operand2 = 5;
    end
    else begin
    // Establecer operandos
    operand1 = $urandom_range(WIDTH);
    operand2 = $urandom_range(WIDTH);
    end
    #10;
    // Realizar suma
    opcode = 2'b00;
    
    $display("Operand1 = %d", operand1);
    $display("Operand2 = %d", operand2);
    $display("Result = %d zero_flag = %b", result,zero_o);
    $display("----------------------------");

    #10;

    // Realizar resta
    opcode = 2'b01;

    $display("Operand1 = %d", operand1);
    $display("Operand2 = %d", operand2);
    $display("Result = %d zero_flag = %b", result,zero_o);
    $display("----------------------------");

    #10;

    // Realizar AND
    opcode = 4'b10;

    $display("Operand1 = %d", operand1);
    $display("Operand2 = %d", operand2);
    $display("Result = %d zero_flag = %b", result,zero_o);
    $display("----------------------------");

    #10;

    // Realizar OR
    opcode = 4'b11;

    $display("Operand1 = %d", operand1);
    $display("Operand2 = %d", operand2);
    $display("Result = %d zero_flag = %b", result,zero_o);
    $display("----------------------------");
    
    #10;

    // Finalizar la simulación

end

    $finish;
end


endmodule

ALU/ALU_tb.vcd
$date
	Wed Apr 10 16:13:55 2024
$end

$version
	Synopsys VCS version R-2020.12-SP2_Full64
$end

$timescale
	1ns
$end

$comment Csum: 1 0d488f4e5ee430fb $end


$scope module ALU_tb $end
$var reg 5 ! operand1 [4:0] $end
$var reg 5 " operand2 [4:0] $end
$var reg 2 # opcode [1:0] $end
$var wire 5 $ result [4:0] $end
$var wire 1 % zero_o $end
$var integer 32 & i $end
$upscope $end

$enddefinitions $end

#0
$dumpvars
1%
b00000 $
b00000000000000000000000000000000 &
b00 #
b00000 !
b00000 "
$end
#10
b00101 !
b00101 "
b01010 $
0%
#30
b01 #
b00000 $
1%
#40
b10 #
b00101 $
0%
#50
b11 #
#60
b00000000000000000000000000000001 &
#70
b00010 !
b00010 "
b00010 $
#80
b00 #
b00100 $
#90
b01 #
b00000 $
1%
#100
b10 #
b00010 $
0%
#110
b11 #
#120
b00000000000000000000000000000010 &
#130
b00001 !
b00000 "
b00001 $
#140
b00 #
#150
b01 #
#160
b10 #
b00000 $
1%
#170
b11 #
b00001 $
0%
#180
b00000000000000000000000000000011 &
#190
b00101 "
b00101 $
#200
b00 #
b00110 $
#210
b01 #
b11100 $
#220
b10 #
b00001 $
#230
b11 #
b00101 $
#240
b00000000000000000000000000000100 &
#250
b00100 !
b00011 "
b00111 $
#260
b00 #
#270
b01 #
b00001 $
#280
b10 #
b00000 $
1%
#290
b11 #
b00111 $
0%
#300
b00000000000000000000000000000101 &
#310
b00000 !
b00101 "
b00101 $
#320
b00 #
#330
b01 #
b11011 $
#340
b10 #
b00000 $
1%
#350
b11 #
b00101 $
0%
#360
b00000000000000000000000000000110 &
#370
b00101 !
b00010 "
b00111 $
#380
b00 #
#390
b01 #
b00011 $
#400
b10 #
b00000 $
1%
#410
b11 #
b00111 $
0%
#420
b00000000000000000000000000000111 &
#430
b00010 !
b00101 "
#440
b00 #
#450
b01 #
b11101 $
#460
b10 #
b00000 $
1%
#470
b11 #
b00111 $
0%
#480
b00000000000000000000000000001000 &
#490
b00101 !
b00000 "
b00101 $
#500
b00 #
#510
b01 #
#520
b10 #
b00000 $
1%
#530
b11 #
b00101 $
0%
#540
b00000000000000000000000000001001 &
#550
b00010 !
b00101 "
b00111 $
#560
b00 #
#570
b01 #
b11101 $
#580
b10 #
b00000 $
1%
#590
b11 #
b00111 $
0%
#600
b00000000000000000000000000001010 &
