Shift/shift.sv
module shift #(parameter N=64)(
input [N-1:0] in,
output [N/2-1:0] out
);

reg [N-1:0]intermedio;
assign intermedio = in << 1;
assign out= {intermedio [N/2-1:0]};


endmodule

Shift/shift_tb.sv
`timescale 1ns / 1ps

module shift_tb;

logic [63:0] in;

logic [31:0] out;

integer i;

shift #() dut(
.in(in),
.out(out)
);

initial begin

$dumpfile("shift_tb.vcd"); // Especifica el nombre del archivo VCD
$dumpvars(1, shift_tb); // Define el alcance de la generación del VCD

in =0;
    for(i=0;i<10;i=i+1) begin
        in=$random;
        #10;
        $display("Valor del imm truncado %b",out);
        #10;


    end
end

endmodule

Shift/shift_tb.vcd
$date
	Wed Apr 10 18:29:38 2024
$end

$version
	Synopsys VCS version R-2020.12-SP2_Full64
$end

$timescale
	1ps
$end

$comment Csum: 1 caa2a3371810130a $end


$scope module shift_tb $end
$var reg 64 ! in [63:0] $end
$var reg 32 " out [31:0] $end
$var integer 32 # i $end
$upscope $end

$enddefinitions $end

#0
$dumpvars
b00000000000000000000000000000000 #
b0000000000000000000000000000000000010010000101010011010100100100 !
b00100100001010100110101001001000 "
$end
#20000
b00000000000000000000000000000001 #
b1111111111111111111111111111111111000000100010010101111010000001 !
b10000001000100101011110100000010 "
#40000
b00000000000000000000000000000010 #
b1111111111111111111111111111111110000100100001001101011000001001 !
b00001001000010011010110000010010 "
#60000
b00000000000000000000000000000011 #
b1111111111111111111111111111111110110001111100000101011001100011 !
b01100011111000001010110011000110 "
#80000
b00000000000000000000000000000100 #
b0000000000000000000000000000000000000110101110010111101100001101 !
b00001101011100101111011000011010 "
#100000
b00000000000000000000000000000101 #
b0000000000000000000000000000000001000110110111111001100110001101 !
b10001101101111110011001100011010 "
#120000
b00000000000000000000000000000110 #
b1111111111111111111111111111111110110010110000101000010001100101 !
b01100101100001010000100011001010 "
#140000
b00000000000000000000000000000111 #
b1111111111111111111111111111111110001001001101110101001000010010 !
b00010010011011101010010000100100 "
#160000
b00000000000000000000000000001000 #
b0000000000000000000000000000000000000000111100111110001100000001 !
b00000001111001111100011000000010 "
#180000
b00000000000000000000000000001001 #
b0000000000000000000000000000000000000110110101111100110100001101 !
b00001101101011111001101000011010 "
#200000
b00000000000000000000000000001010 #
